{
  "parent": "minecraft:recipes/root",
  "rewards": {
    "recipes": [
      "spartanawakens:glaive_crystal_wood"
    ]
  },
  "criteria": {
    "has_crystal_wood_glaive": {
      "trigger": "minecraft:inventory_changed",
      "conditions": {
        "items": [
          {
            "tag": "spartanawakens:crystal_wood"
          }
        ]
      }
    },
    "has_the_recipe": {
      "trigger": "minecraft:recipe_unlocked",
      "conditions": {
        "recipe": "spartanawakens:glaive_crystal_wood"
      }
    }
  },
  "requirements": [
    [
      "has_crystal_wood_glaive",
      "has_the_recipe"
    ]
  ]
}